tf_som/__init__.py
tf_som/layers.py
tf_som/models.py
tf_som/models_test.py
tf_som-0.0.1.dist-info/LICENSE
tf_som-0.0.1.dist-info/METADATA
tf_som-0.0.1.dist-info/WHEEL
tf_som-0.0.1.dist-info/top_level.txt
tf_som-0.0.1.dist-info/RECORD
