Metadata-Version: 2.1
Name: tf-som
Version: 0.0.1
Summary: Self-organizing maps in tensorflow
Home-page: https://github.com/JacobFV/tf-som
Author: Jacob Valdez
Author-email: jacobfv@msn.com
License: MIT
Platform: UNKNOWN
Classifier: License :: OSI Approved :: MIT License
Classifier: Programming Language :: Python :: 3
Classifier: Programming Language :: Python :: 3.7
Requires-Dist: tensorflow (>=2.0.0)
